README.md
setup.py
asyncpool/__init__.py
asyncpool.egg-info/PKG-INFO
asyncpool.egg-info/SOURCES.txt
asyncpool.egg-info/dependency_links.txt
asyncpool.egg-info/top_level.txt